Metadata-Version: 2.4
Name: lxml-qpython
Version: 5.3.0
Summary: Powerful and Pythonic XML processing library combining libxml2/libxslt with the ElementTree API
Home-page: https://pypi.org/project/lxml/
Author: The Lxml Development Team
Author-email: support@qpython.org
License: MIT AND (Apache-2.0 OR BSD-2-Clause)
Classifier: Intended Audience :: Developers
Classifier: Intended Audience :: Education
Classifier: Intended Audience :: Information Technology
Classifier: Intended Audience :: End Users/Desktop
Classifier: License :: OSI Approved :: Apache Software License
Classifier: Operating System :: Android
Classifier: Programming Language :: Python
Classifier: Programming Language :: Python :: 3.12
Classifier: Topic :: Software Development
Dynamic: author
Dynamic: author-email
Dynamic: classifier
Dynamic: description
Dynamic: description-content-type
Dynamic: home-page
Dynamic: license
Dynamic: summary
